README.rst
setup.py
src/asynctask/__init__.py
src/asynctask/backend.py
src/asynctask/manager.py
src/asynctask/task.py
src/m3_asynctask.egg-info/PKG-INFO
src/m3_asynctask.egg-info/SOURCES.txt
src/m3_asynctask.egg-info/dependency_links.txt
src/m3_asynctask.egg-info/top_level.txt