Metadata-Version: 1.1
Name: m3-asynctask
Version: 1.0.0.1
Summary: Расширение django-celery для хранения информации о задачах
Home-page: https://bitbucket.org/barsgroup/asynctask
Author: Ilya Kirov
Author-email: kirov@bars-open.ru
License: MIT
Platform: UNKNOWN
Classifier: Intended Audience :: Developers
Classifier: Environment :: Web Environment
Classifier: Natural Language :: Russian
Classifier: Natural Language :: English
Classifier: Operating System :: OS Independent
Classifier: Programming Language :: Python
Classifier: License :: OSI Approved :: MIT License
Classifier: Development Status :: 5 - Production/Stable
